spnkr/__init__.py
spnkr/client.py
spnkr/errors.py
spnkr/extras.py
spnkr/responses.py
spnkr/xuid.py
spnkr/auth/__init__.py
spnkr/auth/app.py
spnkr/auth/core.py
spnkr/auth/halo.py
spnkr/auth/oauth.py
spnkr/auth/player.py
spnkr/auth/xbox.py
spnkr/film/__init__.py
spnkr/film/api.py
spnkr/film/highlight_events.py
spnkr/film/medal_codes.json
spnkr/film/medals.py
spnkr/models/__init__.py
spnkr/models/base.py
spnkr/models/discovery_ugc.py
spnkr/models/economy.py
spnkr/models/gamecms_hacs.py
spnkr/models/profile.py
spnkr/models/refdata.py
spnkr/models/skill.py
spnkr/models/stats.py
spnkr/models/types.py
spnkr/services/__init__.py
spnkr/services/base.py
spnkr/services/discovery_ugc.py
spnkr/services/economy.py
spnkr/services/gamecms_hacs.py
spnkr/services/profile.py
spnkr/services/skill.py
spnkr/services/stats.py
spnkr-0.10.0.dist-info/licenses/LICENSE
spnkr-0.10.0.dist-info/METADATA
spnkr-0.10.0.dist-info/WHEEL
spnkr-0.10.0.dist-info/top_level.txt
spnkr-0.10.0.dist-info/RECORD
