Metadata-Version: 2.4
Name: spnkr
Version: 0.10.0
Summary: Unofficial Python SDK for the Halo Infinite web API.
Author: Andy Curtis
License: Copyright 2022 Andy Curtis
Project-URL: Homepage, https://github.com/acurtis166/SPNKr
Project-URL: Documentation, https://acurtis166.github.io/SPNKr/
Keywords: halo,infinite,api
Classifier: License :: OSI Approved :: MIT License
Classifier: Programming Language :: Python
Classifier: Programming Language :: Python :: 3
Requires-Python: >=3.11
License-File: LICENSE
Requires-Dist: aiohttp<4.0,>=3.9
Requires-Dist: aiolimiter~=1.0
Requires-Dist: pydantic<3.0,>=2.8
Requires-Dist: bitstring~=4.0
Provides-Extra: cache
Requires-Dist: aiohttp-client-cache>=0.10; extra == "cache"
Dynamic: license-file
